Metadata-Version: 2.1
Name: pyrezfix
Version: 1.1.6
Summary: An open-source wrapper for Hi-Rez Studios API (Paladins, Realm Royale, and Smite), written in Python.
Home-page: https://github.com/antonio272a/pyrezfix
Author: Luis (Lugg) Gustavo
Author-email: the.nonsocial@gmail.com
Maintainer: Luis (Lugg) Gustavo
Maintainer-email: the.nonsocial@gmail.com
License: MIT
Download-URL: https://github.com/antonio272a/pyrezfix/archive/1.1.6.tar.gz
Project-URL: Documentation, https://pyrezfix.readthedocs.io/en/stable/
Project-URL: Tracker, https://github.com/antonio272a/pyrezfix/issues
Project-URL: Say Thanks!, https://saythanks.io/to/luissilva1044894
Project-URL: Source, https://github.com/antonio272a/pyrezfix
Keywords: pyrezfix,hirez,hi-rez,smite,paladins,realmapi,open-source,api,wrapper,library,python,api-wrapper,paladins-api,smitegame,smiteapi,realm-api,realm-royale,python3,python-3,python-3-6
Platform: any
Classifier: Development Status :: 5 - Production/Stable
Classifier: Intended Audience :: Developers
Classifier: License :: OSI Approved :: MIT License
Classifier: Natural Language :: English
Classifier: Operating System :: OS Independent
Classifier: Programming Language :: Python
Classifier: Programming Language :: Python :: 2
Classifier: Programming Language :: Python :: 2.7
Classifier: Programming Language :: Python :: 3
Classifier: Programming Language :: Python :: 3.5
Classifier: Programming Language :: Python :: 3.6
Classifier: Programming Language :: Python :: 3.7
Classifier: Programming Language :: Python :: 3.8
Classifier: Programming Language :: Python :: 3.9
Classifier: Programming Language :: Python :: Implementation :: CPython
Classifier: Programming Language :: Python :: Implementation :: PyPy
Classifier: Topic :: Software Development
Classifier: Topic :: Software Development :: Libraries
Classifier: Topic :: Software Development :: Libraries :: Python Modules
Classifier: Topic :: Utilities
Requires-Python: >=2.7,!=3.0.*,!=3.1.*,!=3.2.*,!=3.3.*,!=3.4.*,<4
Requires-Dist: colorama (<1) ; os_name=="nt"
Requires-Dist: requests (<3) ; python_version >= "2.7"
Provides-Extra: dev
Requires-Dist: pip (~=21.0.1) ; extra == 'dev'
Requires-Dist: pipenv (~=2020.11.15) ; extra == 'dev'
Requires-Dist: setuptools (~=53.0.0) ; extra == 'dev'
Requires-Dist: twine (~=3.3.0) ; extra == 'dev'
Requires-Dist: wheel (~=0.36.2) ; extra == 'dev'
Requires-Dist: sphinx ; extra == 'dev'
Requires-Dist: sphinx-rtd-theme (<1) ; extra == 'dev'
Requires-Dist: sphinxcontrib-websupport ; extra == 'dev'
Requires-Dist: requests (<3) ; (python_version >= "2.7") and extra == 'dev'
Provides-Extra: docs
Requires-Dist: sphinx ; extra == 'docs'
Requires-Dist: sphinx-rtd-theme (<1) ; extra == 'docs'
Requires-Dist: sphinxcontrib-websupport ; extra == 'docs'
Requires-Dist: requests (<3) ; (python_version >= "2.7") and extra == 'docs'
Provides-Extra: httpx
Requires-Dist: httpx (==0.16.*) ; (python_version >= "2.7") and extra == 'httpx'
